mgen/__init__.py
mgen/rotation_matrix_2d.py
mgen/rotation_matrix_3d.py
mgen/rotation_matrix_nd.py
mgen-1.2.1.dist-info/AUTHORS
mgen-1.2.1.dist-info/LICENSE
mgen-1.2.1.dist-info/METADATA
mgen-1.2.1.dist-info/WHEEL
mgen-1.2.1.dist-info/pbr.json
mgen-1.2.1.dist-info/top_level.txt
mgen-1.2.1.dist-info/RECORD
