Metadata-Version: 2.1
Name: mgen
Version: 1.2.1
Summary: Package to generate rotation matrices
Home-page: https://github.com/NOhs/mgen
Author: NOhs
License: BSD
Keywords: matrix, rotations, Euler angles
Classifier: Programming Language :: Python
Classifier: Programming Language :: Python :: 3.8
Classifier: Programming Language :: Python :: 3.9
Classifier: Programming Language :: Python :: 3.10
Classifier: Programming Language :: Python :: 3.11
License-File: LICENSE
